pyPodcastParser/Item.py
pyPodcastParser/Podcast.py
pyPodcastParser/__init__.py
pyPodcastParserPodcastNamespace/Item.py
pyPodcastParserPodcastNamespace/Podcast.py
pyPodcastParserPodcastNamespace/__init__.py
pyPodcastParserPodcastNamespace-2.0.4.dist-info/LICENSE
pyPodcastParserPodcastNamespace-2.0.4.dist-info/METADATA
pyPodcastParserPodcastNamespace-2.0.4.dist-info/WHEEL
pyPodcastParserPodcastNamespace-2.0.4.dist-info/top_level.txt
pyPodcastParserPodcastNamespace-2.0.4.dist-info/RECORD
