Metadata-Version: 2.1
Name: pyPodcastParserPodcastNamespace
Version: 2.0.4
Summary: pyPodcastParserPodcastNamespace is a podcast parser that also includes some podcast namespace parsing capabilities
Home-page: https://github.com/normand1/pyPodcastParser
Author: David Norman
Author-email: david.norman@gmail.com
License: MIT
Keywords: podcast,parser,rss,feed
Platform: UNKNOWN
Classifier: Development Status :: 5 - Production/Stable
Classifier: Intended Audience :: Developers
Classifier: Topic :: Software Development :: Libraries :: Python Modules
Classifier: Topic :: Text Processing :: Markup :: XML
Classifier: License :: OSI Approved :: MIT License
Classifier: Programming Language :: Python :: 2
Classifier: Programming Language :: Python :: 2.6
Classifier: Programming Language :: Python :: 2.7
Classifier: Programming Language :: Python :: 3
Classifier: Programming Language :: Python :: 3.2
Classifier: Programming Language :: Python :: 3.3
Classifier: Programming Language :: Python :: 3.4
Classifier: Programming Language :: Python :: 3.5
Requires-Dist: beautifulsoup4
